ccft_pymarkdown/__init__.py
ccft_pymarkdown/__main__.py
ccft_pymarkdown/_clean.py
ccft_pymarkdown/_restore.py
ccft_pymarkdown/_scan.py
ccft_pymarkdown/console.py
ccft_pymarkdown/context_manager.py
ccft_pymarkdown/py.typed
ccft_pymarkdown/utils/__init__.py
ccft_pymarkdown/utils/click_logging.py
ccft_pymarkdown-3.0.0.dist-info/METADATA
ccft_pymarkdown-3.0.0.dist-info/WHEEL
ccft_pymarkdown-3.0.0.dist-info/entry_points.txt
ccft_pymarkdown-3.0.0.dist-info/licenses/LICENSE
ccft_pymarkdown-3.0.0.dist-info/RECORD
