Metadata-Version: 2.4
Name: CCFT-PyMarkdown
Version: 3.0.0
Summary: ARCHIVED | A Python wrapper around jackdewinter's PyMarkdown linter to suppress errors, caused by custom-formatted tables in Markdown files
Project-URL: Issues, https://github.com/CarrotManMatt/CCFT-PyMarkdown/issues
Project-URL: Repository, https://github.com/CarrotManMatt/CCFT-PyMarkdown
Author-email: Matt Norton <matt@carrotmanmatt.com>
License-Expression: Apache-2.0
License-File: LICENSE
Keywords: linter,markdown,static analysis
Classifier: Development Status :: 7 - Inactive
Classifier: Environment :: Console
Classifier: Intended Audience :: Developers
Classifier: License :: OSI Approved :: Apache Software License
Classifier: Natural Language :: English
Classifier: Operating System :: OS Independent
Classifier: Programming Language :: Python :: 3 :: Only
Classifier: Programming Language :: Python :: 3.12
Classifier: Programming Language :: Python :: 3.13
Classifier: Programming Language :: Python :: 3.14
Classifier: Topic :: Software Development :: Quality Assurance
Classifier: Topic :: Text Processing :: Markup :: Markdown
Classifier: Typing :: Typed
Requires-Python: >=3.12
Requires-Dist: click>=8.1
Requires-Dist: inflect>=7.5
Requires-Dist: pymarkdownlnt>=0.9
Provides-Extra: git-python
Requires-Dist: gitpython>=3.1; extra == 'git-python'
